LighthouseLibrary/LighthouseLibrary.py
LighthouseLibrary/__init__.py
LighthouseLibrary/version.py
rf_lighthouselibrary-1.0a14.dist-info/LICENSE
rf_lighthouselibrary-1.0a14.dist-info/METADATA
rf_lighthouselibrary-1.0a14.dist-info/WHEEL
rf_lighthouselibrary-1.0a14.dist-info/top_level.txt
rf_lighthouselibrary-1.0a14.dist-info/RECORD
